auditmiddleware/__init__.py
auditmiddleware/_api.py
auditmiddleware/_notifier.py
auditmiddleware/tests/__init__.py
auditmiddleware/tests/unit/__init__.py
auditmiddleware/tests/unit/base.py
auditmiddleware/tests/unit/test_audit_filter.py
auditmiddleware/tests/unit/test_audit_middleware.py
auditmiddleware/tests/unit/test_audit_oslo_messaging.py
auditmiddleware/tests/unit/test_logging_notifier.py
auditmiddleware/tests/unit/test_mappings.py
auditmiddleware/tests/unit/utils.py
audit_middleware-1.1.1.dev25.dist-info/LICENSE
audit_middleware-1.1.1.dev25.dist-info/METADATA
audit_middleware-1.1.1.dev25.dist-info/WHEEL
audit_middleware-1.1.1.dev25.dist-info/entry_points.txt
audit_middleware-1.1.1.dev25.dist-info/pbr.json
audit_middleware-1.1.1.dev25.dist-info/top_level.txt
audit_middleware-1.1.1.dev25.dist-info/RECORD
