Metadata-Version: 2.1
Name: audit-middleware
Version: 1.1.1.dev25
Summary: Audit Middleware for OpenStack
Home-page: https://github.com/sapcc/openstack-audit-middleware
Author: SAP SE
Author-email: nathan.oyler@sap.com
Keywords: python,openstack,audit,cadf
Classifier: Development Status :: 4 - Beta
Classifier: Environment :: OpenStack
Classifier: Intended Audience :: Information Technology
Classifier: Intended Audience :: System Administrators
Classifier: License :: OSI Approved :: Apache Software License
Classifier: Operating System :: POSIX :: Linux
Classifier: Programming Language :: Python
Classifier: Programming Language :: Python :: 2
Classifier: Programming Language :: Python :: 2.7
Classifier: Programming Language :: Python :: 3
Classifier: Programming Language :: Python :: 3.5
License-File: LICENSE
Requires-Dist: keystoneauth1 (>=3.4.0)
Requires-Dist: oslo.messaging
Requires-Dist: oslo.config (>=5.2.0)
Requires-Dist: oslo.serialization (!=2.19.1,>=2.18.0)
Requires-Dist: pycadf (!=2.0.0,>=1.1.0)
Requires-Dist: PyYAML
Requires-Dist: requests (>=2.14.2)
Requires-Dist: WebOb (>=1.7.1)
Requires-Dist: six (>=1.10.0)
Provides-Extra: audit_notifications
Requires-Dist: oslo.messaging (!=5.25.0,>=5.24.2) ; extra == 'audit_notifications'
Provides-Extra: test
Requires-Dist: datadog (==0.30.0) ; extra == 'test'
Requires-Dist: hacking (~=6.0.1) ; extra == 'test'
Requires-Dist: flake8-docstrings (~=1.7.0) ; extra == 'test'
Requires-Dist: coverage (!=4.4,>=4.0) ; extra == 'test'
Requires-Dist: fixtures (>=3.0.0) ; extra == 'test'
Requires-Dist: mock (>=3.0.0) ; extra == 'test'
Requires-Dist: oslotest (>=3.8.0) ; extra == 'test'
Requires-Dist: requests-mock (>=1.2.0) ; extra == 'test'
Requires-Dist: stestr (>=2.0.0) ; extra == 'test'
Requires-Dist: testresources (>=2.0.0) ; extra == 'test'
Requires-Dist: testtools (>=2.2.0) ; extra == 'test'
Requires-Dist: WebTest (>=2.0.27) ; extra == 'test'
Requires-Dist: oslo.messaging (>=5.29.0) ; extra == 'test'
Requires-Dist: bandit (>=1.1.0) ; extra == 'test'
